ecs_game/__init__.py
ecs_game/engine.py
ecs_game/flight_engine.py
ecs_game/launch_engine.py
ecs_game-1.6.dist-info/METADATA
ecs_game-1.6.dist-info/WHEEL
ecs_game-1.6.dist-info/licenses/LICENSE
ecs_game-1.6.dist-info/RECORD
